CHANGELOG.md
kperm/__init__.py
kperm/__main__.py
kperm/channel.py
kperm/examples.py
kperm/permeation.py
kperm/utils.py
kperm-0.2.0.dist-info/LICENSE
kperm-0.2.0.dist-info/METADATA
kperm-0.2.0.dist-info/WHEEL
kperm-0.2.0.dist-info/entry_points.txt
kperm-0.2.0.dist-info/RECORD
