Metadata-Version: 2.1
Name: kperm
Version: 0.2.0
Summary: Toolkit for Analysis of Permeation Cycles in Potassium Channels
License: GPL-3.0
Author: Chun Kei (Tom) Lam
Author-email: chun-kei.lam@mpinat.mpg.de
Requires-Python: >=3.8,<3.12
Classifier: License :: OSI Approved :: GNU General Public License v3 (GPLv3)
Classifier: Programming Language :: Python :: 3
Classifier: Programming Language :: Python :: 3.8
Classifier: Programming Language :: Python :: 3.9
Classifier: Programming Language :: Python :: 3.10
Classifier: Programming Language :: Python :: 3.11
Requires-Dist: MDAnalysis (>=2.4.3,<3.0.0)
Requires-Dist: argcomplete (>=3.0.8,<4.0.0)
Requires-Dist: jupyter (>=1.0.0,<2.0.0)
Requires-Dist: matplotlib (>=3.7.1,<4.0.0)
Requires-Dist: networkx (>=3.1,<4.0)
Requires-Dist: numpy (>=1.24.3,<2.0.0)
Requires-Dist: pandas (>=2.0.1,<3.0.0)
Requires-Dist: scipy (>=1.10.1,<2.0.0)
